baseshift/__init__.py
baseshift/auth_oauth.py
baseshift/auth_token.py
baseshift/build_config.py
baseshift/client.py
baseshift/conftest.py
baseshift/db_ping.py
baseshift/tailscale.py
baseshift/test_schema.py
baseshift/utils.py
baseshift/version.py
baseshift/binaries/__init__.py
baseshift/binaries/baseshift-dubhub-ts-forwarder-windows-amd64.exe
baseshift/commands/__init__.py
baseshift/commands/auth.py
baseshift/commands/base.py
baseshift/commands/baseguard.py
baseshift/commands/clone.py
baseshift/commands/dub.py
baseshift/commands/hub.py
baseshift/commands/init.py
baseshift/commands/mcp.py
baseshift/commands/mcp_server.py
baseshift/commands/schema.py
baseshift-2.3.5.dist-info/licenses/LICENSE
baseshift-2.3.5.dist-info/METADATA
baseshift-2.3.5.dist-info/WHEEL
baseshift-2.3.5.dist-info/entry_points.txt
baseshift-2.3.5.dist-info/top_level.txt
baseshift-2.3.5.dist-info/RECORD
