Metadata-Version: 2.4
Name: baseshift
Version: 2.3.5
Summary: Baseshift CLI - Database clone management with Tailscale connectivity
Home-page: https://baseshift.io
License: BSD 2-Clause License
License-File: LICENSE
Requires-Dist: requests
Requires-Dist: importlib-metadata; python_version < "3.8"
Requires-Dist: sentry-sdk
Requires-Dist: psycopg
Requires-Dist: pymysql
Requires-Dist: pymongo
Requires-Dist: httpx
Requires-Dist: mcp
Dynamic: license-file
